setup.py
ciworker/__init__.py
ciworker/arg_parser.py
ciworker/base_worker.py
ciworker/config_parser.py
ciworker/id_generator.py
ciworker/worker_builder.py
ciworker.egg-info/PKG-INFO
ciworker.egg-info/SOURCES.txt
ciworker.egg-info/dependency_links.txt
ciworker.egg-info/pbr.json
ciworker.egg-info/requires.txt
ciworker.egg-info/top_level.txt
test/__init__.py
test/config_parser_test.py