Metadata-Version: 1.1
Name: ciworker
Version: 0.2.0
Summary: Cytoscape CI ciworker service template
Home-page: https://github.com/idekerlab/ci-service-template
Author: Keiichiro Ono
Author-email: kono@ucsd.edu
License: MIT License
Keywords: graph,network,cytoscape
Platform: UNKNOWN
Classifier: Intended Audience :: Science/Research
Classifier: Intended Audience :: Developers
Classifier: Operating System :: OS Independent
Classifier: Development Status :: 3 - Alpha
Classifier: Programming Language :: Python :: 2.7
Classifier: Programming Language :: Python :: 3.4
Classifier: License :: OSI Approved :: MIT License
Classifier: Topic :: Scientific/Engineering :: Information Analysis
Classifier: Topic :: Scientific/Engineering :: Mathematics
